{"title":"Message","notes":[{"title":"Rust Enum","notes":[{"title":"Associated Value","notes":null},{"title":"match","notes":[{"title":"syntax","notes":null},{"title":"extracting associated value","notes":null},{"title":"catch all with _","notes":null}]},{"title":"impl blocks","notes":null}]},{"title":"GetAll","notes":[{"title":"plain c style enum","notes":null}]},{"title":"All","notes":[{"title":"Comes with ToDos","notes":null},{"title":"Vec == List/Array","notes":null},{"title":"All server responses","notes":null}]},{"title":"Add","notes":[{"title":"Comes with ToDo","notes":null}]},{"title":"Update","notes":[{"title":"Comes with ToDo","notes":null}]},{"title":"Remove","notes":[{"title":"Comes with ID","notes":null}]},{"title":"Error","notes":[{"title":"Comes with String","notes":null}]},{"title":"fns","notes":[{"title":"for_error","notes":[{"title":"ctor","notes":null},{"title":"impl trait","notes":null}]},{"title":"to_bytes","notes":[{"title":"wrapper","notes":null}]},{"title":"from_bytes","notes":[{"title":"ctor","notes":null},{"title":"can fail","notes":[{"title":"result","notes":null},{"title":"genaric notation?","notes":null},{"title":"match","notes":null},{"title":"unwrap_or in to_bytes","notes":null}]}]}]}]}